matchmaps/__init__.py
matchmaps/_args.py
matchmaps/_compute_mr_diff.py
matchmaps/_compute_ncs_diff.py
matchmaps/_compute_realspace_diff.py
matchmaps/_diagnostic_plots.py
matchmaps/_parsers.py
matchmaps/_phenix_utils.py
matchmaps/_utils.py
matchmaps/_version_util.py
matchmaps-0.7.1.dist-info/METADATA
matchmaps-0.7.1.dist-info/WHEEL
matchmaps-0.7.1.dist-info/entry_points.txt
matchmaps-0.7.1.dist-info/licenses/LICENSE
matchmaps-0.7.1.dist-info/RECORD
